dictmagic/__init__.py
dictmagic/obj.py
dictmagic/paths.py
dictmagic-0.1.1.dist-info/LICENSE
dictmagic-0.1.1.dist-info/METADATA
dictmagic-0.1.1.dist-info/WHEEL
dictmagic-0.1.1.dist-info/top_level.txt
dictmagic-0.1.1.dist-info/RECORD
