Metadata-Version: 2.1
Name: dictmagic
Version: 0.1.1
Summary: a package that makes it easier to do weird things with python dictionaries
Home-page: https://github.com/mivanit/dictmagic
Author: mivanit
Author-email: miv@knc.ai
License: UNKNOWN
Platform: UNKNOWN
Classifier: Programming Language :: Python :: 3
Classifier: License :: OSI Approved :: GNU General Public License v3 (GPLv3)
Classifier: Operating System :: OS Independent
Requires-Python: >=3.6
